setuptools_scm_node_and_dirty_tag.py
setuptools_scm_node_and_dirty_tag-0.0.0.post0.dist-info/entry_points.txt
setuptools_scm_node_and_dirty_tag-0.0.0.post0.dist-info/WHEEL
setuptools_scm_node_and_dirty_tag-0.0.0.post0.dist-info/METADATA
setuptools_scm_node_and_dirty_tag-0.0.0.post0.dist-info/RECORD
